stix_shifter_modules/aws_athena/__init__.py
stix_shifter_modules/aws_athena/entry_point.py
stix_shifter_modules/aws_athena/configuration/config.json
stix_shifter_modules/aws_athena/configuration/dialects.json
stix_shifter_modules/aws_athena/configuration/lang_en.json
stix_shifter_modules/aws_athena/stix_translation/__init__.py
stix_shifter_modules/aws_athena/stix_translation/json_to_stix_translator.py
stix_shifter_modules/aws_athena/stix_translation/query_constructor.py
stix_shifter_modules/aws_athena/stix_translation/query_translator.py
stix_shifter_modules/aws_athena/stix_translation/transformers.py
stix_shifter_modules/aws_athena/stix_translation/json/guardduty_config.json
stix_shifter_modules/aws_athena/stix_translation/json/guardduty_from_stix_map.json
stix_shifter_modules/aws_athena/stix_translation/json/guardduty_to_stix_map.json
stix_shifter_modules/aws_athena/stix_translation/json/hash_algorithm_map.json
stix_shifter_modules/aws_athena/stix_translation/json/network_protocol_map.json
stix_shifter_modules/aws_athena/stix_translation/json/ocsf_from_stix_map.json
stix_shifter_modules/aws_athena/stix_translation/json/ocsf_to_stix_map.json
stix_shifter_modules/aws_athena/stix_translation/json/operators.json
stix_shifter_modules/aws_athena/stix_translation/json/vpcflow_from_stix_map.json
stix_shifter_modules/aws_athena/stix_translation/json/vpcflow_to_stix_map.json
stix_shifter_modules/aws_athena/stix_translation/json/stix_2_1/guardduty_from_stix_map.json
stix_shifter_modules/aws_athena/stix_translation/json/stix_2_1/ocsf_from_stix_map.json
stix_shifter_modules/aws_athena/stix_translation/json/stix_2_1/to_stix_map.json
stix_shifter_modules/aws_athena/stix_translation/json/stix_2_1/vpcflow_from_stix_map.json
stix_shifter_modules/aws_athena/stix_transmission/__init__.py
stix_shifter_modules/aws_athena/stix_transmission/boto3_client.py
stix_shifter_modules/aws_athena/stix_transmission/delete_connector.py
stix_shifter_modules_aws_athena-8.0.2.dist-info/licenses/AUTHORS.md
stix_shifter_modules_aws_athena-8.0.2.dist-info/licenses/LICENSE.md
stix_shifter_modules_aws_athena-8.0.2.dist-info/licenses/NOTICE
stix_shifter_modules_aws_athena-8.0.2.dist-info/METADATA
stix_shifter_modules_aws_athena-8.0.2.dist-info/WHEEL
stix_shifter_modules_aws_athena-8.0.2.dist-info/top_level.txt
stix_shifter_modules_aws_athena-8.0.2.dist-info/RECORD
